README.md
setup.py
ampscz_anonymize_dicom.egg-info/PKG-INFO
ampscz_anonymize_dicom.egg-info/SOURCES.txt
ampscz_anonymize_dicom.egg-info/dependency_links.txt
ampscz_anonymize_dicom.egg-info/requires.txt
ampscz_anonymize_dicom.egg-info/top_level.txt
anonymize_dicom/__init__.py
anonymize_dicom/anonymize_dicom.py
scripts/ampscz_anonymize_dicom
scripts/ampscz_anonymize_dicom_cli.py