Metadata-Version: 2.1
Name: ampscz-anonymize-dicom
Version: 0.0.15
Summary: AMP-SCZ Dicom anonymizer
Home-page: https://github.com/AMP-SCZ/ampscz_anonymize_dicom
Author: Kevin Cho
Author-email: kevincho@bwh.harvard.edu
Classifier: Programming Language :: Python :: 3
Classifier: License :: OSI Approved :: MIT License
Requires-Python: >=3.7
